pdwinauto/LICENSE
pdwinauto/README.MD
pdwinauto/__init__.py
pdwinauto/requirements.txt
pdwinauto/thirdparty.json
pdwinauto-0.11.dist-info/LICENSE.rst
pdwinauto-0.11.dist-info/METADATA
pdwinauto-0.11.dist-info/WHEEL
pdwinauto-0.11.dist-info/top_level.txt
pdwinauto-0.11.dist-info/RECORD
