Metadata-Version: 2.1
Name: pdwinauto
Version: 0.11
Summary: Use Pandas to find and interact with handles, windows, and elements
Home-page: https://github.com/hansalemaos/pdwinauto
Author: Johannes Fischer
Author-email: <aulasparticularesdealemaosp@gmail.com>
License: MIT
Keywords: automation,pandas,pyautogui,pywinauto,win32,uia
Classifier: Development Status :: 4 - Beta
Classifier: Programming Language :: Python :: 3 :: Only
Classifier: Programming Language :: Python :: 3.9
Classifier: Topic :: Scientific/Engineering :: Visualization
Classifier: Topic :: Software Development :: Libraries :: Python Modules
Classifier: Topic :: Text Editors :: Text Processing
Classifier: Topic :: Text Processing :: General
Classifier: Topic :: Text Processing :: Indexing
Classifier: Topic :: Text Processing :: Filters
Classifier: Topic :: Utilities
License-File: LICENSE.rst
Requires-Dist: a-cv-imwrite-imread-plus
Requires-Dist: a-pandas-ex-apply-ignore-exceptions
Requires-Dist: a-pandas-ex-automate-win32
Requires-Dist: a-pandas-ex-horizontal-explode
Requires-Dist: a-pandas-ex-loc-no-exceptions
Requires-Dist: comtypes
Requires-Dist: ctypes-window-info
Requires-Dist: ctypes-windows
Requires-Dist: files-folders-with-timestamp
Requires-Dist: flatten-everything
Requires-Dist: flexible-partial
Requires-Dist: kthread-sleep
Requires-Dist: mousekey
Requires-Dist: mss
Requires-Dist: numpy
Requires-Dist: pandas
Requires-Dist: PrettyColorPrinter
Requires-Dist: six
